1f208feb8befd053ff71__mypyc.cpython-313-x86_64-linux-gnu.so
structlog_sentry_logger/structlog_sentry.py
structlog_sentry_logger/__init__.cpython-313-x86_64-linux-gnu.so
structlog_sentry_logger/__init__.py
structlog_sentry_logger/_config.py
structlog_sentry_logger/_feature_flags.py
structlog_sentry_logger/structlog_sentry.cpython-313-x86_64-linux-gnu.so
structlog_sentry_logger/_feature_flags.cpython-313-x86_64-linux-gnu.so
structlog_sentry_logger/py.typed
structlog_sentry_logger/_config.cpython-313-x86_64-linux-gnu.so
structlog_sentry_logger-1.6.2.dist-info/WHEEL
structlog_sentry_logger-1.6.2.dist-info/METADATA
structlog_sentry_logger-1.6.2.dist-info/RECORD
structlog_sentry_logger-1.6.2.dist-info/licenses/LICENSE
