Metadata-Version: 2.4
Name: structlog-sentry-logger
Version: 1.6.2
Summary: Log without the setup via a pre-configured structlog logger with optional Sentry integration
Project-URL: Homepage, https://github.com/TeoZosa/structlog-sentry-logger
Project-URL: Repository, https://github.com/TeoZosa/structlog-sentry-logger
Project-URL: Changelog, https://github.com/TeoZosa/structlog-sentry-logger/releases
Author: Teo Zosa
License-Expression: Apache-2.0
License-File: LICENSE
Keywords: log,logging,sentry,structlog,structlog-sentry,structure,structured,structured logging
Classifier: Intended Audience :: Developers
Classifier: License :: OSI Approved :: Apache Software License
Classifier: Natural Language :: English
Classifier: Operating System :: OS Independent
Classifier: Programming Language :: Python
Classifier: Programming Language :: Python :: 3
Classifier: Programming Language :: Python :: 3.9
Classifier: Programming Language :: Python :: 3.10
Classifier: Programming Language :: Python :: 3.11
Classifier: Programming Language :: Python :: 3.12
Classifier: Programming Language :: Python :: 3.13
Classifier: Programming Language :: Python :: Implementation :: CPython
Classifier: Topic :: Software Development :: Libraries :: Python Modules
Requires-Python: <3.14,>=3.9
Requires-Dist: colorama; platform_system == 'Windows'
Requires-Dist: gitpython
Requires-Dist: orjson
Requires-Dist: python-dotenv
Requires-Dist: rich
Requires-Dist: structlog
Provides-Extra: dev
Requires-Dist: black>=25.1; extra == 'dev'
Requires-Dist: cruft>=2.16.0; extra == 'dev'
Requires-Dist: darglint>=1.5.8; extra == 'dev'
Requires-Dist: mutmut<3.0.0,>=2.5.1; extra == 'dev'
Requires-Dist: mypy>=1.14; extra == 'dev'
Requires-Dist: pre-commit>=4.1.0; extra == 'dev'
Requires-Dist: pytest-benchmark[histogram]>=4.0.0; extra == 'dev'
Requires-Dist: pytest-cov>=6.0.0; extra == 'dev'
Requires-Dist: pytest-emoji>=0.2.0; extra == 'dev'
Requires-Dist: pytest-forked>=1.6.0; extra == 'dev'
Requires-Dist: pytest-mock>=3.14.0; extra == 'dev'
Requires-Dist: pytest-sugar>=1.0.0; extra == 'dev'
Requires-Dist: pytest-xdist>=3.6.1; extra == 'dev'
Requires-Dist: pytest>=8.3.4; extra == 'dev'
Requires-Dist: tox-gh>=1.5.0; extra == 'dev'
Requires-Dist: tox-wheel>=1.0.0; extra == 'dev'
Requires-Dist: tox>=3.28.0; extra == 'dev'
Requires-Dist: xdoctest[optional]>=1.2.0; extra == 'dev'
Provides-Extra: docs
Requires-Dist: emoji<3.0.0,>=1.6.1; extra == 'docs'
Requires-Dist: importlib-metadata>=3.4.0; extra == 'docs'
Requires-Dist: myst-parser<3.1,>=0.15; extra == 'docs'
Requires-Dist: pygments>=2.9.0; extra == 'docs'
Requires-Dist: sphinx-autoapi<4.0.0,>=1.8.1; extra == 'docs'
Requires-Dist: sphinx-rtd-theme<3.1.0,>=0.5.1; extra == 'docs'
Requires-Dist: sphinx>=4.1.2; extra == 'docs'
Requires-Dist: types-emoji<3.0.0,>=1.2.4; extra == 'docs'
Provides-Extra: sentry
Requires-Dist: sentry-sdk; extra == 'sentry'
